LICENSE
NOTICE
README.md
pyproject.toml
setup.py
apache_dubbo.egg-info/PKG-INFO
apache_dubbo.egg-info/SOURCES.txt
apache_dubbo.egg-info/dependency_links.txt
apache_dubbo.egg-info/requires.txt
apache_dubbo.egg-info/top_level.txt
dubbo/__init__.py
dubbo/__version__.py
dubbo/bootstrap.py
dubbo/classes.py
dubbo/client.py
dubbo/configs.py
dubbo/deliverers.py
dubbo/loggers.py
dubbo/node.py
dubbo/server.py
dubbo/types.py
dubbo/url.py
dubbo/utils.py
dubbo/cluster/__init__.py
dubbo/cluster/_interfaces.py
dubbo/cluster/directories.py
dubbo/cluster/failfast_cluster.py
dubbo/cluster/loadbalances.py
dubbo/cluster/monitor/__init__.py
dubbo/cluster/monitor/cpu.py
dubbo/compression/__init__.py
dubbo/compression/_interfaces.py
dubbo/compression/bzip2s.py
dubbo/compression/gzips.py
dubbo/compression/identities.py
dubbo/constants/__init__.py
dubbo/constants/common_constants.py
dubbo/constants/config_constants.py
dubbo/constants/logger_constants.py
dubbo/constants/registry_constants.py
dubbo/extension/__init__.py
dubbo/extension/extension_loader.py
dubbo/extension/registries.py
dubbo/loadbalance/__init__.py
dubbo/loadbalance/_interfaces.py
dubbo/protocol/__init__.py
dubbo/protocol/_interfaces.py
dubbo/protocol/invocation.py
dubbo/protocol/triple/__init__.py
dubbo/protocol/triple/coders.py
dubbo/protocol/triple/constants.py
dubbo/protocol/triple/exceptions.py
dubbo/protocol/triple/invoker.py
dubbo/protocol/triple/metadata.py
dubbo/protocol/triple/protocol.py
dubbo/protocol/triple/results.py
dubbo/protocol/triple/status.py
dubbo/protocol/triple/streams.py
dubbo/protocol/triple/call/__init__.py
dubbo/protocol/triple/call/_interfaces.py
dubbo/protocol/triple/call/client_call.py
dubbo/protocol/triple/call/server_call.py
dubbo/protocol/triple/stream/__init__.py
dubbo/protocol/triple/stream/_interfaces.py
dubbo/protocol/triple/stream/client_stream.py
dubbo/protocol/triple/stream/server_stream.py
dubbo/proxy/__init__.py
dubbo/proxy/_interfaces.py
dubbo/proxy/callables.py
dubbo/proxy/handlers.py
dubbo/registry/__init__.py
dubbo/registry/_interfaces.py
dubbo/registry/protocol.py
dubbo/registry/zookeeper/__init__.py
dubbo/registry/zookeeper/_interfaces.py
