Metadata-Version: 2.1
Name: apache-dubbo
Version: 3.0.0b1
Summary: Python Implementation For Apache Dubbo.
Home-page: https://github.com/apache/dubbo-python
Author: Apache Dubbo Community
Author-email: dev@dubbo.apache.org
License: Apache License Version 2.0
Keywords: dubbo,rpc,dubbo-python,http2,network
Classifier: Development Status :: 4 - Beta
Classifier: Intended Audience :: Developers
Classifier: License :: OSI Approved :: Apache Software License
Classifier: Operating System :: OS Independent
Classifier: Programming Language :: Python :: 3
Classifier: Programming Language :: Python :: 3 :: Only
Classifier: Programming Language :: Python :: 3.11
Classifier: Framework :: AsyncIO
Classifier: Topic :: Internet
Classifier: Topic :: Internet :: WWW/HTTP
Classifier: Topic :: Internet :: WWW/HTTP :: HTTP Servers
Classifier: Topic :: Software Development :: Libraries
Classifier: Topic :: Software Development :: Libraries :: Python Modules
Classifier: Topic :: System :: Networking
Requires-Python: >=3.11
Provides-Extra: zookeeper
License-File: LICENSE
License-File: NOTICE
